django_forms_plus/__init__.py
django_forms_plus/apps.py
django_forms_plus/errors.py
django_forms_plus/form_helper.py
django_forms_plus/forms.py
django_forms_plus/layout.py
django_forms_plus/response.py
django_forms_plus/spec.py
django_forms_plus/static/django_forms_plus/dfp.build.js
django_forms_plus/static/django_forms_plus/dfp.build.js.LICENSE.txt
django_forms_plus/static/django_forms_plus/dfp.build.js.map
django_forms_plus/types.py
django_forms_plus/views.py
django_forms_plus/widgets.py
django_forms_plus-0.14.1.dist-info/LICENSE
django_forms_plus-0.14.1.dist-info/METADATA
django_forms_plus-0.14.1.dist-info/WHEEL
django_forms_plus-0.14.1.dist-info/RECORD
