Metadata-Version: 2.1
Name: django_forms_plus
Version: 0.14.1
Summary: React-powered forms for Django
Home-page: https://github.com/versusbassz/django_forms_plus
License: MIT
Keywords: django,forms,react
Author: Vladimir Sklyar
Author-email: versus.post@gmail.com
Requires-Python: >=3.10,<4.0
Classifier: Development Status :: 3 - Alpha
Classifier: Environment :: Web Environment
Classifier: Framework :: Django
Classifier: Framework :: Django :: 3.2
Classifier: Intended Audience :: Developers
Classifier: License :: OSI Approved :: MIT License
Classifier: Operating System :: OS Independent
Classifier: Programming Language :: JavaScript
Classifier: Programming Language :: Python :: 3
Classifier: Programming Language :: Python :: 3.10
Classifier: Programming Language :: Python :: 3.11
Classifier: Programming Language :: Python :: 3.12
Classifier: Topic :: Internet :: WWW/HTTP
Classifier: Topic :: Internet :: WWW/HTTP :: Dynamic Content
Classifier: Topic :: Software Development :: User Interfaces
Requires-Dist: pydantic (>=2.7.1,<3.0.0)
Requires-Dist: ujson (>=5.9.0,<6.0.0)
Project-URL: Repository, https://github.com/versusbassz/django_forms_plus
